{
  "graph": {
    "nodes": {
      "DATABASE:shared-db": {
        "id": "DATABASE:shared-db",
        "name": "shared-db",
        "kind": "DATABASE"
      },
      "SERVICE:auth": {
        "id": "SERVICE:auth",
        "name": "auth",
        "kind": "SERVICE"
      },
      "SERVICE:inventory": {
        "id": "SERVICE:inventory",
        "name": "inventory",
        "kind": "SERVICE"
      },
      "SERVICE:orders": {
        "id": "SERVICE:orders",
        "name": "orders",
        "kind": "SERVICE"
      },
      "SERVICE:web": {
        "id": "SERVICE:web",
        "name": "web",
        "kind": "SERVICE"
      }
    },
    "edges": [
      {
        "from": "SERVICE:web",
        "to": "SERVICE:auth",
        "kind": "CALLS",
        "attrs": {
          "dep_kind": "rest",
          "sync": true
        }
      },
      {
        "from": "SERVICE:web",
        "to": "SERVICE:orders",
        "kind": "CALLS",
        "attrs": {
          "dep_kind": "rest",
          "sync": true
        }
      },
      {
        "from": "SERVICE:orders",
        "to": "SERVICE:inventory",
        "kind": "CALLS",
        "attrs": {
          "dep_kind": "rest",
          "sync": true
        }
      },
      {
        "from": "SERVICE:orders",
        "to": "DATABASE:shared-db",
        "kind": "CALLS",
        "attrs": {
          "dep_kind": "rest",
          "sync": true
        }
      },
      {
        "from": "SERVICE:inventory",
        "to": "DATABASE:shared-db",
        "kind": "CALLS",
        "attrs": {
          "dep_kind": "rest",
          "sync": true
        }
      },
      {
        "from": "SERVICE:auth",
        "to": "DATABASE:shared-db",
        "kind": "CALLS",
        "attrs": {
          "dep_kind": "rest",
          "sync": true
        }
      }
    ]
  },
  "dot_path": "/app/out/runs/29ce05a4b7ffe4b2/graph.dot",
  "svg_path": "/app/out/runs/29ce05a4b7ffe4b2/graph.svg",
  "detections": [
    {
      "kind": "ui_orchestrator",
      "severity": "MEDIUM",
      "title": "UI orchestrator",
      "summary": "UI directly orchestrates multiple backend services",
      "nodes": [
        "SERVICE:web",
        "SERVICE:auth",
        "SERVICE:orders"
      ],
      "edges": [],
      "evidence": {
        "min_out": 2,
        "sync_targets": 2,
        "targets": 2,
        "ui": "SERVICE:web"
      }
    }
  ]
}